regxon/__init__.py
regxon/common.py
regxon/html.py
regxon-0.0.9.dist-info/LICENSE
regxon-0.0.9.dist-info/METADATA
regxon-0.0.9.dist-info/WHEEL
regxon-0.0.9.dist-info/top_level.txt
regxon-0.0.9.dist-info/RECORD
