Metadata-Version: 2.1
Name: regxon
Version: 0.0.9
Summary: RegXon is a powerful validator, sanitizer and content parser that you're searching for decades.
Home-page: https://github.com/Bishwas-py/regxon
Author: Bishwas Bhandari
Author-email: bishwasbh@gmail.com
Classifier: Programming Language :: Python :: 3
Classifier: Programming Language :: Python :: 3.6
Classifier: Programming Language :: Python :: 3.7
Classifier: License :: OSI Approved :: MIT License
Classifier: Operating System :: OS Independent
License-File: LICENSE
Requires-Dist: beautifulsoup4 (==4.11.1)
